mysingle_quant/__init__.py
mysingle_quant/auth/README.md
mysingle_quant/auth/__init__.py
mysingle_quant/auth/authenticate.py
mysingle_quant/auth/cache.py
mysingle_quant/auth/deps.py
mysingle_quant/auth/exception_handlers.py
mysingle_quant/auth/exceptions.py
mysingle_quant/auth/init_data.py
mysingle_quant/auth/middleware.py
mysingle_quant/auth/models.py
mysingle_quant/auth/oauth_manager.py
mysingle_quant/auth/types.py
mysingle_quant/auth/user_manager.py
mysingle_quant/auth/oauth2/clients.py
mysingle_quant/auth/router/__init__.py
mysingle_quant/auth/router/auth.py
mysingle_quant/auth/router/common.py
mysingle_quant/auth/router/oauth2.py
mysingle_quant/auth/router/oauth_management.py
mysingle_quant/auth/router/register.py
mysingle_quant/auth/router/reset.py
mysingle_quant/auth/router/users.py
mysingle_quant/auth/router/verify.py
mysingle_quant/auth/schemas/__init__.py
mysingle_quant/auth/schemas/auth.py
mysingle_quant/auth/schemas/oauth2.py
mysingle_quant/auth/schemas/user.py
mysingle_quant/auth/security/cookie.py
mysingle_quant/auth/security/jwt.py
mysingle_quant/auth/security/password.py
mysingle_quant/base/__init__.py
mysingle_quant/base/enums.py
mysingle_quant/base/models.py
mysingle_quant/base/schemas.py
mysingle_quant/clients/__init__.py
mysingle_quant/clients/base_client.py
mysingle_quant/core/__init__.py
mysingle_quant/core/app_factory.py
mysingle_quant/core/config.py
mysingle_quant/core/db.py
mysingle_quant/core/logging_config.py
mysingle_quant/core/service_types.py
mysingle_quant/database/__init__.py
mysingle_quant/database/duckdb_manager.py
mysingle_quant/email/__init__.py
mysingle_quant/email/email_gen.py
mysingle_quant/email/email_sending.py
mysingle_quant/email/email_token.py
mysingle_quant/email/email-templates/logo.png
mysingle_quant/health/__init__.py
mysingle_quant/health/checker.py
mysingle_quant/health/router.py
mysingle_quant/health/schemas.py
mysingle_quant/metrics/IMPROVEMENT_REPORT.md
mysingle_quant/metrics/README.md
mysingle_quant-0.1.113.dist-info/METADATA
mysingle_quant-0.1.113.dist-info/WHEEL
mysingle_quant-0.1.113.dist-info/RECORD
